{
  "lang":"ru",
  "name":"pipeline",
  "version":"0.0.0",
  "spacy_version":">=3.5.3,<3.6.0",
  "description":"",
  "author":"",
  "email":"",
  "url":"",
  "license":"",
  "spacy_git_version":"512241e12",
  "vectors":{
    "width":0,
    "vectors":0,
    "keys":0,
    "name":null,
    "mode":"default"
  },
  "labels":{
    "tok2vec":[

    ],
    "ner":[
      "ABILITIES",
      "ACESS",
      "ANIMAL",
      "APP",
      "ARAB",
      "ARCHITECTURE",
      "ART",
      "AVIA",
      "BEADS",
      "BEAUTY",
      "BEE",
      "BOARDGAME",
      "BOOK",
      "BRAIN",
      "BUISNESS",
      "CARE",
      "CHINA",
      "CHRIST",
      "CITY",
      "COFFE",
      "COMPGAMES",
      "COMPUTER",
      "CONTROL",
      "COOKING",
      "COSMOS",
      "COURSE",
      "CULTURE",
      "CURRENT",
      "DANCE",
      "DESIGN",
      "EDUCATION",
      "ENGLISH",
      "EVDOKIM",
      "EVTUSH",
      "FAMILYTIES",
      "FILM",
      "FIRSTAID",
      "FLORA",
      "FOTO",
      "FRANCE",
      "GAME",
      "GEOGRAPHY",
      "GERMAN",
      "GRAMMAR",
      "GREEK",
      "HEALTH",
      "HELPGRANDCHILD",
      "HISTORY",
      "HOME",
      "INTERACTIVE",
      "INTERNET",
      "ITALY",
      "JAPAN",
      "LANGUAGUE",
      "LAW",
      "LEISURE",
      "MEDICINE",
      "MMA",
      "MOBIL",
      "MONEY",
      "MOSCOW",
      "MSU",
      "MUSIC",
      "NEIBOUR",
      "NEWCAREER",
      "NUTRITION",
      "ONLINESERVICE",
      "PAPER",
      "PET",
      "PHYLOSOPHY",
      "PHYSICAL",
      "PLASTIC",
      "POLITICS",
      "PROGRAMMER",
      "PSYHO",
      "QUIZ",
      "RELATIONS",
      "RELIGION",
      "REPAIR",
      "RIDE",
      "RULES",
      "RUSSIA",
      "SAFE",
      "SCIENCE",
      "SEW",
      "SINGING",
      "SOCIALMEDIA",
      "SOCIETY",
      "SPAIN",
      "SPEECH",
      "SPORT",
      "SPORTSECTION",
      "STUDY",
      "TECH",
      "THEATRE",
      "TOUR",
      "TRAVEL",
      "TURKEY",
      "VEHICLE",
      "VOLONTER",
      "WOOD"
    ]
  },
  "pipeline":[
    "tok2vec",
    "ner"
  ],
  "components":[
    "tok2vec",
    "ner"
  ],
  "disabled":[

  ],
  "performance":{
    "ents_f":0.9310156676,
    "ents_p":0.912591687,
    "ents_r":0.9501988862,
    "ents_per_type":{
      "COURSE":{
        "p":0.9287749288,
        "r":0.9731343284,
        "f":0.9504373178
      },
      "MONEY":{
        "p":0.9272727273,
        "r":0.9622641509,
        "f":0.9444444444
      },
      "LAW":{
        "p":0.9333333333,
        "r":1.0,
        "f":0.9655172414
      },
      "BUISNESS":{
        "p":0.9333333333,
        "r":0.9333333333,
        "f":0.9333333333
      },
      "NEWCAREER":{
        "p":0.8684210526,
        "r":0.9705882353,
        "f":0.9166666667
      },
      "STUDY":{
        "p":0.9678961749,
        "r":0.9867688022,
        "f":0.9772413793
      },
      "SOCIETY":{
        "p":0.8723404255,
        "r":0.8039215686,
        "f":0.8367346939
      },
      "EDUCATION":{
        "p":0.95,
        "r":1.0,
        "f":0.9743589744
      },
      "ABILITIES":{
        "p":0.8603603604,
        "r":0.8215053763,
        "f":0.8404840484
      },
      "LEISURE":{
        "p":0.8630136986,
        "r":0.984375,
        "f":0.9197080292
      },
      "CULTURE":{
        "p":0.8793103448,
        "r":0.9444444444,
        "f":0.9107142857
      },
      "RELATIONS":{
        "p":0.859223301,
        "r":0.921875,
        "f":0.8894472362
      },
      "ART":{
        "p":0.9005847953,
        "r":0.9221556886,
        "f":0.9112426036
      },
      "THEATRE":{
        "p":0.9090909091,
        "r":1.0,
        "f":0.9523809524
      },
      "CURRENT":{
        "p":0.8333333333,
        "r":0.8536585366,
        "f":0.843373494
      },
      "TECH":{
        "p":0.75,
        "r":0.9,
        "f":0.8181818182
      },
      "HOME":{
        "p":0.8979591837,
        "r":0.9166666667,
        "f":0.9072164948
      },
      "HELPGRANDCHILD":{
        "p":0.8703703704,
        "r":0.9791666667,
        "f":0.9215686275
      },
      "CARE":{
        "p":0.7142857143,
        "r":1.0,
        "f":0.8333333333
      },
      "MEDICINE":{
        "p":0.8020833333,
        "r":0.8953488372,
        "f":0.8461538462
      },
      "NUTRITION":{
        "p":0.90625,
        "r":0.935483871,
        "f":0.9206349206
      },
      "PSYHO":{
        "p":0.8934911243,
        "r":0.94375,
        "f":0.9179331307
      },
      "FIRSTAID":{
        "p":0.875,
        "r":0.7777777778,
        "f":0.8235294118
      },
      "DESIGN":{
        "p":0.8421052632,
        "r":0.96,
        "f":0.8971962617
      },
      "APP":{
        "p":0.7916666667,
        "r":0.9047619048,
        "f":0.8444444444
      },
      "TRAVEL":{
        "p":0.90625,
        "r":0.8285714286,
        "f":0.8656716418
      },
      "ONLINESERVICE":{
        "p":0.9428571429,
        "r":0.9166666667,
        "f":0.9295774648
      },
      "CITY":{
        "p":0.9459459459,
        "r":1.0,
        "f":0.9722222222
      },
      "INTERNET":{
        "p":0.9206349206,
        "r":0.9666666667,
        "f":0.9430894309
      },
      "SAFE":{
        "p":0.9411764706,
        "r":1.0,
        "f":0.9696969697
      },
      "COMPUTER":{
        "p":0.95,
        "r":1.0,
        "f":0.9743589744
      },
      "NEIBOUR":{
        "p":0.75,
        "r":0.8571428571,
        "f":0.8
      },
      "HISTORY":{
        "p":0.9210526316,
        "r":0.9589041096,
        "f":0.9395973154
      },
      "PLASTIC":{
        "p":0.90625,
        "r":1.0,
        "f":0.9508196721
      },
      "TOUR":{
        "p":0.9436619718,
        "r":0.9710144928,
        "f":0.9571428571
      },
      "DANCE":{
        "p":0.9574468085,
        "r":0.9782608696,
        "f":0.9677419355
      },
      "SPAIN":{
        "p":0.95,
        "r":1.0,
        "f":0.9743589744
      },
      "CHINA":{
        "p":1.0,
        "r":1.0,
        "f":1.0
      },
      "PHYSICAL":{
        "p":0.9508196721,
        "r":0.9720670391,
        "f":0.9613259669
      },
      "FLORA":{
        "p":0.8823529412,
        "r":0.9868421053,
        "f":0.9316770186
      },
      "SEW":{
        "p":0.9019607843,
        "r":0.9928057554,
        "f":0.9452054795
      },
      "REPAIR":{
        "p":0.9545454545,
        "r":1.0,
        "f":0.976744186
      },
      "WOOD":{
        "p":1.0,
        "r":1.0,
        "f":1.0
      },
      "COOKING":{
        "p":0.8378378378,
        "r":0.96875,
        "f":0.8985507246
      },
      "BEAUTY":{
        "p":0.875,
        "r":0.9130434783,
        "f":0.8936170213
      },
      "SPORT":{
        "p":1.0,
        "r":1.0,
        "f":1.0
      },
      "BOOK":{
        "p":0.8615384615,
        "r":0.9256198347,
        "f":0.8924302789
      },
      "GRAMMAR":{
        "p":0.8778625954,
        "r":0.9745762712,
        "f":0.9236947791
      },
      "PHYLOSOPHY":{
        "p":0.8571428571,
        "r":1.0,
        "f":0.9230769231
      },
      "SPEECH":{
        "p":0.8282828283,
        "r":0.9213483146,
        "f":0.8723404255
      },
      "ENGLISH":{
        "p":0.9615384615,
        "r":0.9615384615,
        "f":0.9615384615
      },
      "LANGUAGUE":{
        "p":0.9558823529,
        "r":0.9923664122,
        "f":0.9737827715
      },
      "MUSIC":{
        "p":0.90625,
        "r":0.8923076923,
        "f":0.8992248062
      },
      "SINGING":{
        "p":1.0,
        "r":1.0,
        "f":1.0
      },
      "FOTO":{
        "p":0.96875,
        "r":1.0,
        "f":0.9841269841
      },
      "BEADS":{
        "p":1.0,
        "r":1.0,
        "f":1.0
      },
      "JAPAN":{
        "p":1.0,
        "r":1.0,
        "f":1.0
      },
      "FRANCE":{
        "p":1.0,
        "r":1.0,
        "f":1.0
      },
      "PAPER":{
        "p":0.9,
        "r":1.0,
        "f":0.9473684211
      },
      "FAMILYTIES":{
        "p":0.8837209302,
        "r":0.95,
        "f":0.9156626506
      },
      "MMA":{
        "p":1.0,
        "r":1.0,
        "f":1.0
      },
      "BRAIN":{
        "p":0.8965517241,
        "r":0.962962963,
        "f":0.9285714286
      },
      "HEALTH":{
        "p":0.8722222222,
        "r":0.9075144509,
        "f":0.8895184136
      },
      "RIDE":{
        "p":1.0,
        "r":1.0,
        "f":1.0
      },
      "SPORTSECTION":{
        "p":1.0,
        "r":1.0,
        "f":1.0
      },
      "GAME":{
        "p":1.0,
        "r":1.0,
        "f":1.0
      },
      "RUSSIA":{
        "p":0.9607843137,
        "r":0.98,
        "f":0.9702970297
      },
      "ACESS":{
        "p":0.7368421053,
        "r":1.0,
        "f":0.8484848485
      },
      "COMPGAMES":{
        "p":0.84,
        "r":0.9545454545,
        "f":0.8936170213
      },
      "SOCIALMEDIA":{
        "p":0.9054054054,
        "r":0.9710144928,
        "f":0.9370629371
      },
      "VOLONTER":{
        "p":1.0,
        "r":1.0,
        "f":1.0
      },
      "INTERACTIVE":{
        "p":0.8333333333,
        "r":1.0,
        "f":0.9090909091
      },
      "FILM":{
        "p":0.9375,
        "r":0.9677419355,
        "f":0.9523809524
      },
      "MOBIL":{
        "p":0.90625,
        "r":0.8787878788,
        "f":0.8923076923
      },
      "MOSCOW":{
        "p":0.9436619718,
        "r":0.9178082192,
        "f":0.9305555556
      },
      "COFFE":{
        "p":1.0,
        "r":1.0,
        "f":1.0
      },
      "ARCHITECTURE":{
        "p":1.0,
        "r":1.0,
        "f":1.0
      },
      "GERMAN":{
        "p":0.9473684211,
        "r":0.9473684211,
        "f":0.9473684211
      },
      "ITALY":{
        "p":0.9333333333,
        "r":1.0,
        "f":0.9655172414
      },
      "POLITICS":{
        "p":1.0,
        "r":1.0,
        "f":1.0
      },
      "RELIGION":{
        "p":0.8333333333,
        "r":0.9090909091,
        "f":0.8695652174
      },
      "EVDOKIM":{
        "p":1.0,
        "r":1.0,
        "f":1.0
      },
      "MSU":{
        "p":1.0,
        "r":1.0,
        "f":1.0
      },
      "EVTUSH":{
        "p":1.0,
        "r":1.0,
        "f":1.0
      },
      "GEOGRAPHY":{
        "p":0.84,
        "r":0.9130434783,
        "f":0.875
      },
      "BEE":{
        "p":0.9166666667,
        "r":0.9166666667,
        "f":0.9166666667
      },
      "CONTROL":{
        "p":0.6,
        "r":1.0,
        "f":0.75
      },
      "PROGRAMMER":{
        "p":1.0,
        "r":0.5,
        "f":0.6666666667
      },
      "COSMOS":{
        "p":1.0,
        "r":1.0,
        "f":1.0
      },
      "PET":{
        "p":0.875,
        "r":1.0,
        "f":0.9333333333
      },
      "ANIMAL":{
        "p":1.0,
        "r":0.8181818182,
        "f":0.9
      },
      "AVIA":{
        "p":1.0,
        "r":1.0,
        "f":1.0
      },
      "VEHICLE":{
        "p":0.75,
        "r":1.0,
        "f":0.8571428571
      },
      "SCIENCE":{
        "p":1.0,
        "r":1.0,
        "f":1.0
      },
      "QUIZ":{
        "p":0.5,
        "r":0.5,
        "f":0.5
      },
      "RULES":{
        "p":0.0,
        "r":0.0,
        "f":0.0
      },
      "BOARDGAME":{
        "p":1.0,
        "r":1.0,
        "f":1.0
      },
      "ARAB":{
        "p":1.0,
        "r":1.0,
        "f":1.0
      },
      "TURKEY":{
        "p":1.0,
        "r":1.0,
        "f":1.0
      },
      "GREEK":{
        "p":1.0,
        "r":1.0,
        "f":1.0
      },
      "CHRIST":{
        "p":1.0,
        "r":0.8888888889,
        "f":0.9411764706
      }
    },
    "tok2vec_loss":984.3976305425,
    "ner_loss":11181.0218290128
  }
}